<?xml version="1.0" encoding="utf-8"?>
<ManifestInput xmlns:xsi="http://www.w3.org/2001/XMLSchema-instance" xmlns:xsd="http://www.w3.org/2001/XMLSchema" xmlns="http://www.clearcanvas.ca">
  <Files>
    <File name="plugins\ClearCanvas.ImageViewer.Volume.Mpr.dll" checksum="true" />
    <File name="plugins\ClearCanvas.ImageViewer.Volume.Mpr.View.WinForms.dll" checksum="true" />
    <File name="plugins\vtkCommon.dll" checksum="true" />
    <File name="plugins\vtkCommonDotNet.dll" checksum="true" />
    <File name="plugins\vtkFiltering.dll" checksum="true" />
    <File name="plugins\vtkFilteringDotNet.dll" checksum="true" />
    <File name="plugins\vtkImaging.dll" checksum="true" />
    <File name="plugins\vtkImagingDotNet.dll" checksum="true" />
    <File name="plugins\vtksys.dll" checksum="true" />
  </Files>
</ManifestInput>
