<?xml version="1.0" encoding="utf-8"?>
<enum class="AllergyAllergenType">
	<enum-value code="DA">
		<value>Drug Allergy</value>
		<description></description>
	</enum-value>
	<enum-value code="FA">
		<value>Food Allergy</value>
		<description></description>
	</enum-value>
	<enum-value code="MA">
		<value>Miscellaneous Allergy</value>
		<description></description>
	</enum-value>
	<enum-value code="MC">
		<value>Miscellaneous Contraindication</value>
		<description></description>
	</enum-value>
	<enum-value code="EA">
		<value>Environmental Allergy</value>
		<description></description>
	</enum-value>
	<enum-value code="AA">
		<value>Animal Allergy</value>
		<description></description>
	</enum-value>
	<enum-value code="PA">
		<value>Plant Allergy</value>
		<description></description>
	</enum-value>
	<enum-value code="LA">
		<value>Pollen Allergy</value>
		<description></description>
	</enum-value>
</enum>
